Peewee392ZhongwenWendang/README.md
Peewee392ZhongwenWendang/__init__.py
Peewee392ZhongwenWendang/__main__.py
Peewee392ZhongwenWendang/file.epub
Peewee392ZhongwenWendang/index.html
Peewee392ZhongwenWendang/css/__init__.py
Peewee392ZhongwenWendang/css/annotations.css
Peewee392ZhongwenWendang/css/main.css
Peewee392ZhongwenWendang/css/normalize.css
Peewee392ZhongwenWendang/css/popup.css
Peewee392ZhongwenWendang/font/__init__.py
Peewee392ZhongwenWendang/font/fontello.eot
Peewee392ZhongwenWendang/font/fontello.svg
Peewee392ZhongwenWendang/font/fontello.ttf
Peewee392ZhongwenWendang/font/fontello.woff
Peewee392ZhongwenWendang/img/__init__.py
Peewee392ZhongwenWendang/img/annotator-glyph-sprite.png
Peewee392ZhongwenWendang/img/annotator-icon-sprite.png
Peewee392ZhongwenWendang/img/apple-touch-icon.png
Peewee392ZhongwenWendang/img/cancelfullscreen.png
Peewee392ZhongwenWendang/img/close.png
Peewee392ZhongwenWendang/img/fullscreen.png
Peewee392ZhongwenWendang/img/loader.gif
Peewee392ZhongwenWendang/img/menu-icon.png
Peewee392ZhongwenWendang/img/save.png
Peewee392ZhongwenWendang/img/saved.png
Peewee392ZhongwenWendang/img/settings-s.png
Peewee392ZhongwenWendang/img/settings.png
Peewee392ZhongwenWendang/img/star.png
Peewee392ZhongwenWendang/js/__init__.py
Peewee392ZhongwenWendang/js/epub.js
Peewee392ZhongwenWendang/js/epub.min.js
Peewee392ZhongwenWendang/js/epub.min.map
Peewee392ZhongwenWendang/js/hooks.min.js
Peewee392ZhongwenWendang/js/hooks.min.map
Peewee392ZhongwenWendang/js/reader.js
Peewee392ZhongwenWendang/js/reader.js.map
Peewee392ZhongwenWendang/js/reader.min.js
Peewee392ZhongwenWendang/js/reader.min.map
Peewee392ZhongwenWendang/js/hooks/__init__.py
Peewee392ZhongwenWendang/js/hooks/extensions/__init__.py
Peewee392ZhongwenWendang/js/hooks/extensions/highlight.js
Peewee392ZhongwenWendang/js/libs/__init__.py
Peewee392ZhongwenWendang/js/libs/jquery.min.js
Peewee392ZhongwenWendang/js/libs/localforage.min.js
Peewee392ZhongwenWendang/js/libs/screenfull.js
peewee_3_9_2_zhongwen_wendang-2024.3.4.0.dist-info/METADATA
peewee_3_9_2_zhongwen_wendang-2024.3.4.0.dist-info/WHEEL
peewee_3_9_2_zhongwen_wendang-2024.3.4.0.dist-info/entry_points.txt
peewee_3_9_2_zhongwen_wendang-2024.3.4.0.dist-info/top_level.txt
peewee_3_9_2_zhongwen_wendang-2024.3.4.0.dist-info/RECORD
